jpxtime-0.0.4.dist-info/METADATA
jpxtime-0.0.4.dist-info/RECORD
jpxtime-0.0.4.dist-info/WHEEL
jpxtime-0.0.4.dist-info/top_level.txt
jpxtime-0.0.4.dist-info/metadata.json
jpxtime-0.0.4.dist-info/DESCRIPTION.rst
jpxtime/__init__.py
jpxtime/holiday_cache
jpxtime/sq_cache
