Metadata-Version: 2.0
Name: jpxtime
Version: 0.0.4
Summary: Japan Exchange Delivatives(Index) trading schedule and trading hours
Home-page: UNKNOWN
Author: driller
Author-email: UNKNOWN
License: UNKNOWN
Platform: UNKNOWN
Requires-Dist: python-dateutil
Requires-Dist: PyYAML
